{"2251": {"id": 2251, "name": "Reserve League", "country": "Qatar", "countryId": 158}, "2252": {"id": 2252, "name": "Alagoano 2", "country": "Brazil", "countryId": 35}, "2253": {"id": 2253, "name": "Amazonense 2", "country": "Brazil", "countryId": 35}, "2254": {"id": 2254, "name": "West Asia Championship U23", "country": "Asia", "countryId": 2}, "2255": {"id": 2255, "name": "IV Liga", "country": "Poland", "countryId": 155}, "2256": {"id": 2256, "name": "Cearense Women", "country": "Brazil", "countryId": 35}, "2257": {"id": 2257, "name": "Potiguar U20", "country": "Brazil", "countryId": 35}, "2258": {"id": 2258, "name": "CAF Women's Champions League", "country": "Africa", "countryId": 3}, "2259": {"id": 2259, "name": "Paraense B1", "country": "Brazil", "countryId": 35}, "2260": {"id": 2260, "name": "Alagoano U20", "country": "Brazil", "countryId": 35}, "2261": {"id": 2261, "name": "Amazonense Women", "country": "Brazil", "countryId": 35}, "2262": {"id": 2262, "name": "Women's Play-offs 2/3", "country": "Japan", "countryId": 102}, "2263": {"id": 2263, "name": "Women's Play-offs 1/2", "country": "Thailand", "countryId": 191}, "2264": {"id": 2264, "name": "South Central Series", "country": "New Zealand", "countryId": 141}, "2265": {"id": 2265, "name": "Women's South Central Series", "country": "New Zealand", "countryId": 141}, "2266": {"id": 2266, "name": "Liga 2 Feminin", "country": "Romania", "countryId": 159}, "2267": {"id": 2267, "name": "Liga TDP", "country": "Mexico", "countryId": 129}, "2268": {"id": 2268, "name": "Sergipano Women", "country": "Brazil", "countryId": 35}, "2269": {"id": 2269, "name": "Paraense Women", "country": "Brazil", "countryId": 35}, "2270": {"id": 2270, "name": "Paraense U20", "country": "Brazil", "countryId": 35}, "2271": {"id": 2271, "name": "Cupa Rom\u00e2niei U19", "country": "Romania", "countryId": 159}, "2272": {"id": 2272, "name": "MLS Generation Cup U15", "country": "USA", "countryId": 203}, "2273": {"id": 2273, "name": "Supercopa", "country": "Paraguay", "countryId": 152}, "2274": {"id": 2274, "name": "Hampshire Senior Cup", "country": "England", "countryId": 68}, "2275": {"id": 2275, "name": "Copa Conecta", "country": "Mexico", "countryId": 129}}