{"276": {"id": 276, "name": "FA Cup", "country": "China PR", "countryId": 49}, "277": {"id": 277, "name": "Cup", "country": "South Africa", "countryId": 175}, "278": {"id": 278, "name": "OFC Champions League", "country": "Oceania", "countryId": 6}, "279": {"id": 279, "name": "1. Division", "country": "Kazakhstan", "countryId": 104}, "280": {"id": 280, "name": "UEFA U21 Championship", "country": "Europe", "countryId": 7}, "281": {"id": 281, "name": "Tournoi Maurice Revello", "country": "World", "countryId": 1}, "283": {"id": 283, "name": "A-League Men", "country": "Australia", "countryId": 19}, "284": {"id": 284, "name": "FIFA Club World Cup", "country": "World", "countryId": 1}, "285": {"id": 285, "name": "League Cup", "country": "Republic of Ireland", "countryId": 98}, "286": {"id": 286, "name": "Play-offs 1/2", "country": "Netherlands", "countryId": 138}, "287": {"id": 287, "name": "Primera Divisi\u00f3n Femenina", "country": "Spain", "countryId": 176}, "288": {"id": 288, "name": "CONMEBOL Copa America", "country": "South America", "countryId": 5}, "289": {"id": 289, "name": "Toppserien", "country": "Norway", "countryId": 146}, "290": {"id": 290, "name": "Frauen Bundesliga", "country": "Germany", "countryId": 80}, "291": {"id": 291, "name": "Damallsvenskan", "country": "Sweden", "countryId": 184}, "293": {"id": 293, "name": "Serie A Women", "country": "Italy", "countryId": 100}, "294": {"id": 294, "name": "Super Cup", "country": "Denmark", "countryId": 61}, "296": {"id": 296, "name": "NPFL", "country": "Nigeria", "countryId": 144}, "297": {"id": 297, "name": "CONMEBOL Sudamericana", "country": "South America", "countryId": 5}, "298": {"id": 298, "name": "Super Cup", "country": "Ukraine", "countryId": 201}, "299": {"id": 299, "name": "2. SNL", "country": "Slovenia", "countryId": 172}, "300": {"id": 300, "name": "Super Cup", "country": "Slovakia", "countryId": 171}}